bank_management/__init__.py
bank_management/start.py
bank_management/investment/__init__.py
bank_management/investment/investment.py
bank_management/investment/investment_test.py
bank_management/investment/manage_investment.py
bank_management/user/__init__.py
bank_management/user/admin.py
bank_management/user/client.py
bank_management/user/user_test.py
bank_management-0.0.1.dist-info/METADATA
bank_management-0.0.1.dist-info/WHEEL
bank_management-0.0.1.dist-info/top_level.txt
bank_management-0.0.1.dist-info/RECORD
