Metadata-Version: 2.1
Name: bank-management
Version: 0.0.1
Summary: An project for DATA 533, UBCO
Author-email: Alan <zhangmuqing2011@163.com>, Yuyang <yuyangpeng15@gmail.com>
Project-URL: Homepage, https://github.com/pengyuyang-315/step3_banking_management
Project-URL: Issues, https://github.com/pengyuyang-315/step3_banking_management/issues
Classifier: Programming Language :: Python :: 3
Classifier: License :: OSI Approved :: MIT License
Classifier: Operating System :: OS Independent
Requires-Python: >=3.8
